README.md
setup.py
week/__init__.py
week/week.py
week.egg-info/PKG-INFO
week.egg-info/SOURCES.txt
week.egg-info/dependency_links.txt
week.egg-info/entry_points.txt
week.egg-info/requires.txt
week.egg-info/top_level.txt