Metadata-Version: 1.1
Name: week
Version: 0.0.5
Summary: A week package enable you to use week easily
Home-page: https://github.com/ramwin/week
Author: Xiang Wang
Author-email: ramwin@qq.com
License: MIT
Keywords: datetime week
Platform: UNKNOWN
Classifier: Development Status :: 3 - Alpha
Classifier: Intended Audience :: Developers
Classifier: Topic :: Software Development :: Build Tools
Classifier: License :: OSI Approved :: MIT License
Classifier: Programming Language :: Python :: 2
Classifier: Programming Language :: Python :: 2.7
Classifier: Programming Language :: Python :: 3
Classifier: Programming Language :: Python :: 3.3
Classifier: Programming Language :: Python :: 3.4
Classifier: Programming Language :: Python :: 3.5
